pretix_bitpay/__init__.py
pretix_bitpay/apps.py
pretix_bitpay/models.py
pretix_bitpay/payment.py
pretix_bitpay/signals.py
pretix_bitpay/urls.py
pretix_bitpay/views.py
pretix_bitpay/locale/django.pot
pretix_bitpay/locale/ar/LC_MESSAGES/django.mo
pretix_bitpay/locale/ar/LC_MESSAGES/django.po
pretix_bitpay/locale/ca/LC_MESSAGES/django.mo
pretix_bitpay/locale/ca/LC_MESSAGES/django.po
pretix_bitpay/locale/cs/LC_MESSAGES/django.mo
pretix_bitpay/locale/cs/LC_MESSAGES/django.po
pretix_bitpay/locale/da/LC_MESSAGES/django.mo
pretix_bitpay/locale/da/LC_MESSAGES/django.po
pretix_bitpay/locale/de/LC_MESSAGES/django.mo
pretix_bitpay/locale/de/LC_MESSAGES/django.po
pretix_bitpay/locale/de_Informal/.gitkeep
pretix_bitpay/locale/de_Informal/LC_MESSAGES/django.mo
pretix_bitpay/locale/de_Informal/LC_MESSAGES/django.po
pretix_bitpay/locale/el/LC_MESSAGES/django.mo
pretix_bitpay/locale/el/LC_MESSAGES/django.po
pretix_bitpay/locale/es/LC_MESSAGES/django.mo
pretix_bitpay/locale/es/LC_MESSAGES/django.po
pretix_bitpay/locale/fi/LC_MESSAGES/django.mo
pretix_bitpay/locale/fi/LC_MESSAGES/django.po
pretix_bitpay/locale/fr/LC_MESSAGES/django.mo
pretix_bitpay/locale/fr/LC_MESSAGES/django.po
pretix_bitpay/locale/hr/LC_MESSAGES/django.mo
pretix_bitpay/locale/hr/LC_MESSAGES/django.po
pretix_bitpay/locale/it/LC_MESSAGES/django.mo
pretix_bitpay/locale/it/LC_MESSAGES/django.po
pretix_bitpay/locale/ja/LC_MESSAGES/django.mo
pretix_bitpay/locale/ja/LC_MESSAGES/django.po
pretix_bitpay/locale/lv/LC_MESSAGES/django.mo
pretix_bitpay/locale/lv/LC_MESSAGES/django.po
pretix_bitpay/locale/nl/LC_MESSAGES/django.mo
pretix_bitpay/locale/nl/LC_MESSAGES/django.po
pretix_bitpay/locale/nl_BE/LC_MESSAGES/django.mo
pretix_bitpay/locale/nl_BE/LC_MESSAGES/django.po
pretix_bitpay/locale/nl_Informal/LC_MESSAGES/django.mo
pretix_bitpay/locale/nl_Informal/LC_MESSAGES/django.po
pretix_bitpay/locale/pl/LC_MESSAGES/django.mo
pretix_bitpay/locale/pl/LC_MESSAGES/django.po
pretix_bitpay/locale/pl_Informal/LC_MESSAGES/django.mo
pretix_bitpay-1.5.2.dist-info/LICENSE
pretix_bitpay-1.5.2.dist-info/METADATA
pretix_bitpay-1.5.2.dist-info/WHEEL
pretix_bitpay-1.5.2.dist-info/entry_points.txt
pretix_bitpay-1.5.2.dist-info/top_level.txt
pretix_bitpay-1.5.2.dist-info/RECORD
