Metadata-Version: 2.1
Name: pretix-bitpay
Version: 1.5.2
Summary: This plugin allows accepting crypto currency payments in pretix via BitPay-compatible payment providers.
Author-email: pretix team <support@pretix.eu>
Maintainer-email: pretix team <support@pretix.eu>
License: Copyright 2018 Raphael Michel
Project-URL: homepage, https://github.com/pretix/pretix-bitpay
Keywords: pretix
Requires-Python: >=3.9
License-File: LICENSE
Requires-Dist: btcpay-python
